source_zendesk_sell/__init__.py
source_zendesk_sell/manifest.yaml
source_zendesk_sell/run.py
source_zendesk_sell/schemas/call_outcomes.json
source_zendesk_sell/schemas/calls.json
source_zendesk_sell/schemas/collaborations.json
source_zendesk_sell/schemas/contacts.json
source_zendesk_sell/schemas/deal_sources.json
source_zendesk_sell/schemas/deal_unqualified_reasons.json
source_zendesk_sell/schemas/deals.json
source_zendesk_sell/schemas/lead_conversions.json
source_zendesk_sell/schemas/lead_sources.json
source_zendesk_sell/schemas/lead_unqualified_reasons.json
source_zendesk_sell/schemas/leads.json
source_zendesk_sell/schemas/loss_reasons.json
source_zendesk_sell/schemas/notes.json
source_zendesk_sell/schemas/orders.json
source_zendesk_sell/schemas/pipelines.json
source_zendesk_sell/schemas/products.json
source_zendesk_sell/schemas/stages.json
source_zendesk_sell/schemas/tags.json
source_zendesk_sell/schemas/tasks.json
source_zendesk_sell/schemas/text_messages.json
source_zendesk_sell/schemas/users.json
source_zendesk_sell/schemas/visit_outcomes.json
source_zendesk_sell/schemas/visits.json
source_zendesk_sell/source.py
airbyte_source_zendesk_sell-0.2.14.dist-info/METADATA
airbyte_source_zendesk_sell-0.2.14.dist-info/WHEEL
airbyte_source_zendesk_sell-0.2.14.dist-info/entry_points.txt
airbyte_source_zendesk_sell-0.2.14.dist-info/RECORD
